earthkit/aggregate/__init__.py
earthkit/aggregate/climatology.py
earthkit/aggregate/general.py
earthkit/aggregate/spatial.py
earthkit/aggregate/temporal.py
earthkit/aggregate/tools.py
earthkit/aggregate/version.py
ek_aggregate-0.1.2.dist-info/LICENSE
ek_aggregate-0.1.2.dist-info/METADATA
ek_aggregate-0.1.2.dist-info/WHEEL
ek_aggregate-0.1.2.dist-info/top_level.txt
ek_aggregate-0.1.2.dist-info/RECORD
