Metadata-Version: 2.1
Name: ek-aggregate
Version: 0.1.2
Summary: Aggregation tools for meteorological and climate data.
License: Apache License
Classifier: Development Status :: 2 - Pre-Alpha
Classifier: Intended Audience :: Science/Research
Classifier: License :: OSI Approved :: Apache Software License
Classifier: Operating System :: OS Independent
Classifier: Programming Language :: Python
Classifier: Programming Language :: Python :: 3
Classifier: Programming Language :: Python :: 3.10
Classifier: Topic :: Scientific/Engineering
License-File: LICENSE
Requires-Dist: xarray >=2022.3.0
Requires-Dist: numpy >=1.18
Requires-Dist: earthkit-data >=0.3.0
Requires-Dist: geopandas
